GraphLearner/Grid.py
GraphLearner/__init__.py
GraphLearner_mits92-0.0.1.dist-info/LICENSE
GraphLearner_mits92-0.0.1.dist-info/METADATA
GraphLearner_mits92-0.0.1.dist-info/WHEEL
GraphLearner_mits92-0.0.1.dist-info/top_level.txt
GraphLearner_mits92-0.0.1.dist-info/RECORD
