Metadata-Version: 2.1
Name: GraphLearner-mits92
Version: 0.0.1
Summary: To help make working with graphs easier to develop intuition.
Home-page: UNKNOWN
Author: Preston Ward
Author-email: preston.ward@go.tarleton.edu
License: UNKNOWN
Platform: UNKNOWN
Classifier: Programming Language :: Python :: 3
Classifier: License :: OSI Approved :: MIT License
Classifier: Operating System :: OS Independent
Requires-Python: >=3.6
Requires-Dist: networkx
Requires-Dist: matplotlib
